MANIFEST.in
README.rst
setup.py
docs/HISTORY.txt
docs/LICENSE.GPL
docs/LICENSE.txt
docs/TODO.txt
ftw/__init__.py
ftw.structlog.egg-info/PKG-INFO
ftw.structlog.egg-info/SOURCES.txt
ftw.structlog.egg-info/dependency_links.txt
ftw.structlog.egg-info/entry_points.txt
ftw.structlog.egg-info/namespace_packages.txt
ftw.structlog.egg-info/not-zip-safe
ftw.structlog.egg-info/requires.txt
ftw.structlog.egg-info/top_level.txt
ftw/structlog/__init__.py
ftw/structlog/collector.py
ftw/structlog/configure.zcml
ftw/structlog/logger.py
ftw/structlog/sqltime.py
ftw/structlog/subscribers.py
ftw/structlog/testing.py
ftw/structlog/demo/__init__.py
ftw/structlog/demo/configure.zcml
ftw/structlog/demo/views.py
ftw/structlog/tests/__init__.py
ftw/structlog/tests/test_fluent_logging.py
ftw/structlog/tests/test_logger_setup.py
ftw/structlog/tests/test_logging.py